auto_usage/__init__.py
auto_usage/__main__.py
auto_usage/auto_usage.py
auto_usage-1.0.1.dist-info/METADATA
auto_usage-1.0.1.dist-info/WHEEL
auto_usage-1.0.1.dist-info/entry_points.txt
auto_usage-1.0.1.dist-info/top_level.txt
auto_usage-1.0.1.dist-info/RECORD
