Metadata-Version: 2.1
Name: auto-usage
Version: 1.0.1
Summary: A python tool for agenerating or auto-updating usage of python cli tools.
Home-page: https://github.com/zhangxianbing/auto-usage
Author: zhangxianbing
License: UNKNOWN
Platform: UNKNOWN
Requires-Python: >=3.6
